cloudaux/__about__.py
cloudaux/__init__.py
cloudaux/decorators.py
cloudaux/exceptions.py
cloudaux/aws/__init__.py
cloudaux/aws/autoscaling.py
cloudaux/aws/decorators.py
cloudaux/aws/ec2.py
cloudaux/aws/elb.py
cloudaux/aws/elbv2.py
cloudaux/aws/events.py
cloudaux/aws/events_bus.py
cloudaux/aws/glacier.py
cloudaux/aws/iam.py
cloudaux/aws/lambda_function.py
cloudaux/aws/resource_groups_tagging.py
cloudaux/aws/route53.py
cloudaux/aws/s3.py
cloudaux/aws/sg.py
cloudaux/aws/sns.py
cloudaux/aws/sqs.py
cloudaux/aws/sts.py
cloudaux/gcp/__init__.py
cloudaux/gcp/auth.py
cloudaux/gcp/config.py
cloudaux/gcp/crm.py
cloudaux/gcp/decorators.py
cloudaux/gcp/gcpcache.py
cloudaux/gcp/gcs.py
cloudaux/gcp/iam.py
cloudaux/gcp/utils.py
cloudaux/gcp/gce/__init__.py
cloudaux/gcp/gce/address.py
cloudaux/gcp/gce/disk.py
cloudaux/gcp/gce/firewall.py
cloudaux/gcp/gce/forwarding_rule.py
cloudaux/gcp/gce/instance.py
cloudaux/gcp/gce/network.py
cloudaux/gcp/gce/project.py
cloudaux/gcp/gce/zone.py
cloudaux/openstack/__init__.py
cloudaux/openstack/decorators.py
cloudaux/openstack/object_container.py
cloudaux/openstack/utils.py
cloudaux/orchestration/__init__.py
cloudaux/orchestration/aws/__init__.py
cloudaux/orchestration/aws/arn.py
cloudaux/orchestration/aws/elb.py
cloudaux/orchestration/aws/elbv2.py
cloudaux/orchestration/aws/events.py
cloudaux/orchestration/aws/glacier.py
cloudaux/orchestration/aws/image.py
cloudaux/orchestration/aws/lambda_function.py
cloudaux/orchestration/aws/s3.py
cloudaux/orchestration/aws/sg.py
cloudaux/orchestration/aws/sqs.py
cloudaux/orchestration/aws/vpc.py
cloudaux/orchestration/aws/iam/__init__.py
cloudaux/orchestration/aws/iam/group.py
cloudaux/orchestration/aws/iam/managed_policy.py
cloudaux/orchestration/aws/iam/role.py
cloudaux/orchestration/aws/iam/saml_provider.py
cloudaux/orchestration/aws/iam/server_certificate.py
cloudaux/orchestration/aws/iam/user.py
cloudaux/orchestration/gcp/__init__.py
cloudaux/orchestration/gcp/gce/__init__.py
cloudaux-1.9.6.dist-info/AUTHORS
cloudaux-1.9.6.dist-info/LICENSE
cloudaux-1.9.6.dist-info/METADATA
cloudaux-1.9.6.dist-info/WHEEL
cloudaux-1.9.6.dist-info/top_level.txt
cloudaux-1.9.6.dist-info/RECORD
