Metadata-Version: 2.1
Name: cloudaux
Version: 1.9.6
Summary: Cloud Auxiliary is a python wrapper and orchestration module for interacting with cloud providers
Home-page: https://github.com/Netflix-Skunkworks/cloudaux
Author: The Cloudaux Developers
Author-email: oss@netflix.com
License: UNKNOWN
Platform: UNKNOWN
Classifier: Programming Language :: Python :: 3
Classifier: Programming Language :: Python :: 3.6
Classifier: Programming Language :: Python :: 3.7
Classifier: Programming Language :: Python :: 3.8
License-File: LICENSE
License-File: AUTHORS
Requires-Dist: boto3
Requires-Dist: botocore
Requires-Dist: boto (>=2.41.0)
Requires-Dist: joblib (>=0.9.4)
Requires-Dist: inflection
Requires-Dist: flagpole (>=1.0.1)
Requires-Dist: defusedxml
Requires-Dist: six (>=1.11.0)
Provides-Extra: dev
Provides-Extra: docs
Provides-Extra: gcp
Requires-Dist: google-api-python-client (>=1.6.1) ; extra == 'gcp'
Requires-Dist: google-cloud-storage (==0.22.0) ; extra == 'gcp'
Requires-Dist: oauth2client (>=4.1.2) ; extra == 'gcp'
Provides-Extra: openstack
Requires-Dist: openstacksdk (>=0.13.0) ; extra == 'openstack'
Provides-Extra: tests
Requires-Dist: pytest ; extra == 'tests'
Requires-Dist: pytest-cov ; extra == 'tests'
Requires-Dist: moto ; extra == 'tests'
Requires-Dist: mock ; extra == 'tests'
Requires-Dist: coveralls ; extra == 'tests'
Requires-Dist: tox ; extra == 'tests'
Requires-Dist: flake8 ; extra == 'tests'
